single_cell_metabolomics/__init__.py
single_cell_metabolomics/config.py
single_cell_metabolomics/database.py
single_cell_metabolomics/features.py
single_cell_metabolomics/filtration.py
single_cell_metabolomics/plots.py
single_cell_metabolomics/post_msdial.py
single_cell_metabolomics/preparation.py
single_cell_metabolomics/spectra_stats.py
single_cell_metabolomics/modeling/__init__.py
single_cell_metabolomics/modeling/predict.py
single_cell_metabolomics/modeling/train.py
single_cell_metabolomics-0.1.41.dist-info/METADATA
single_cell_metabolomics-0.1.41.dist-info/WHEEL
single_cell_metabolomics-0.1.41.dist-info/entry_points.txt
single_cell_metabolomics-0.1.41.dist-info/licenses/LICENSE
single_cell_metabolomics-0.1.41.dist-info/RECORD
