Metadata-Version: 2.4
Name: single_cell_metabolomics
Version: 0.1.41
Summary: Analysis tools for single-cell metabolome data.
Project-URL: homepage, https://github.com/archerkuo9006/ylc-single-cell-metabolomics
Author-email: Archer Kuo <archerkuo9006@gmail.com>
License-File: LICENSE
Requires-Python: <=3.13,>=3.11
Requires-Dist: dotenv>=0.9.9
Requires-Dist: duckdb>=1.4.2
Requires-Dist: ipykernel>=7.1.0
Requires-Dist: loguru>=0.7.3
Requires-Dist: matplotlib>=3.10.7
Requires-Dist: numpy>=2.3.4
Requires-Dist: pandas>=2.3.3
Requires-Dist: pathlib>=1.0.1
Requires-Dist: psycopg[binary]>=3.2.12
Requires-Dist: pyarrow>=22.0.0
Requires-Dist: pyopenms>=3.4.0
Requires-Dist: scipy>=1.16.3
Requires-Dist: tqdm>=4.67.1
Requires-Dist: typer>=0.20.0
Requires-Dist: typing>=3.10.0.0
